<PAMDataset>
  <PAMRasterBand band="1">
    <Histograms>
      <HistItem>
        <HistMin>-2.914459228515625</HistMin>
        <HistMax>13.18569946289062</HistMax>
        <BucketCount>256</BucketCount>
        <IncludeOutOfRange>1</IncludeOutOfRange>
        <Approximate>0</Approximate>
        <HistCounts>5|37|199|651|1277|2377|2331|1520|1034|979|764|597|460|332|220|613|1426|1743|1272|1086|1353|1732|1155|792|406|340|316|229|261|428|437|359|286|257|312|273|305|288|268|302|303|368|291|354|336|308|307|365|308|358|336|337|404|379|417|420|522|446|490|475|450|539|473|504|469|528|533|501|540|482|567|523|513|566|574|555|570|566|539|550|547|597|635|679|678|649|693|709|790|829|945|903|916|1016|1015|986|1202|1059|1042|1030|1004|1103|886|914|865|845|916|754|816|762|726|691|676|604|640|587|542|497|518|508|434|472|356|344|350|447|344|356|415|381|339|375|329|334|340|341|284|322|245|286|271|243|252|222|226|244|205|222|205|207|187|161|206|189|194|228|292|344|395|393|445|455|514|561|576|635|660|680|705|656|682|657|623|619|602|564|648|633|647|482|530|517|468|476|413|444|425|355|381|334|297|377|286|358|291|321|344|399|466|542|737|785|926|1213|1579|1616|2351|2770|2747|3137|3524|3880|3706|4470|5001|5399|5420|6120|6523|6649|5713|6492|6305|5888|5441|4608|4936|4412|4190|3875|3222|3419|2950|3156|3159|3071|3044|3100|3082|2785|2452|2215|1914|1344|950|555|506|423|338|197|142|114|51|24|5|1</HistCounts>
      </HistItem>
    </Histograms>
    <Metadata>
      <MDI key="RepresentationType">ATHEMATIC</MDI>
      <MDI key="STATISTICS_COVARIANCES">22.6666335504561</MDI>
      <MDI key="STATISTICS_EXCLUDEDVALUES"></MDI>
      <MDI key="STATISTICS_MAXIMUM">13.185699462891</MDI>
      <MDI key="STATISTICS_MEAN">7.7611305663049</MDI>
      <MDI key="STATISTICS_MINIMUM">-2.9144592285156</MDI>
      <MDI key="STATISTICS_SKIPFACTORX">1</MDI>
      <MDI key="STATISTICS_SKIPFACTORY">1</MDI>
      <MDI key="STATISTICS_STDDEV">4.7609488077962</MDI>
    </Metadata>
  </PAMRasterBand>
</PAMDataset>
